avroconsumer.py
avroconsumer-1.2.0.dist-info/LICENSE
avroconsumer-1.2.0.dist-info/METADATA
avroconsumer-1.2.0.dist-info/WHEEL
avroconsumer-1.2.0.dist-info/top_level.txt
avroconsumer-1.2.0.dist-info/RECORD
