Metadata-Version: 2.1
Name: avroconsumer
Version: 1.2.0
Summary: Base consumer class for working with Avro datums
Home-page: https://github.com/gmr/avroconsumer
Maintainer: Gavin M. Roy
Maintainer-email: gavinr@aweber.com
License: BSDv3
Platform: UNKNOWN
Classifier: Development Status :: 5 - Production/Stable
Classifier: Intended Audience :: Developers
Classifier: License :: OSI Approved :: BSD License
Classifier: Operating System :: OS Independent
Classifier: Programming Language :: Python :: 2
Classifier: Programming Language :: Python :: 2.7
Classifier: Programming Language :: Python :: 3
Classifier: Programming Language :: Python :: 3.5
Classifier: Programming Language :: Python :: 3.6
Classifier: Programming Language :: Python :: 3.7
Classifier: Topic :: Software Development :: Libraries
Classifier: Topic :: Software Development :: Libraries :: Python Modules
Requires-Dist: rejected
Requires-Dist: fastavro
Requires-Dist: requests
